vc6_cuda-7.34.0.dist-info/DELVEWHEEL
vc6_cuda-7.34.0.dist-info/METADATA
vc6_cuda-7.34.0.dist-info/RECORD
vc6_cuda-7.34.0.dist-info/top_level.txt
vc6_cuda-7.34.0.dist-info/WHEEL
vc6_cuda-7.34.0.dist-info/licenses/LICENSE.txt
vc6_cuda.libs/.load-order-vc6_cuda-7.34.0
vc6_cuda.libs/msvcp140-ece13b15c395121e9b540eef76b2fedb.dll
vc6_cuda.libs/nvrtc-builtins64_129.dll
vc6_cuda.libs/nvrtc64_120_0-0cc63349fedffeec1660b30955e8028b.dll
vc6_cuda.libs/vcruntime140_1-83c7b3de58551c6dac9fffed753d253e.dll
vnova/vc6_cuda/codec.py
vnova/vc6_cuda/PRIVACY.md
vnova/vc6_cuda/README.md
vnova/vc6_cuda/utils.py
vnova/vc6_cuda/vc6il.py
vnova/vc6_cuda/Vc6Utils.py
vnova/vc6_cuda/_PyVc6IL.pyd
vnova/vc6_cuda/_PyVc6ILUtils.pyd
vnova/vc6_cuda/__init__.py
